Workbook

Sheet Основные_Данные
A1: Год | B1: Чистая розничная выручка, млрд ₽ | C1: Выручка, млрд ₽ | D1: Валовая прибыль, млрд ₽ | E1: Валовая маржа | F1: Скорр. EBITDA, млрд ₽ | G1: EBITDA маржа | H1: Чистая прибыль, млрд ₽ | I1: Чистая маржа | J1: Торговая площадь, тыс. м² | K1: Количество магазинов | L1: Количество покупок, млн
A2: 2021 | B2: 2194 | C2: 2205 | D2: 553.4 | E2: 0.251 | F2: 164.4 | G2: 0.075 | H2: 52.4 | I2: 0.024 | J2: 8296 | K2: 19067 | L2: 5707
A3: 2022 | B3: 2596 | C3: 2605 | D3: 626.7 | E3: 0.241 | F3: 190.5 | G3: 0.073 | H3: 51.2 | I3: 0.02 | J3: 9015 | K3: 21259 | L3: 6299
A4: 2023 | B4: 3129 | C4: 3146 | D4: 757.8 | E4: 0.241 | F4: 218.5 | G4: 0.069 | H4: 90.3 | I4: 0.029 | J4: 10109 | K4: 24390 | L4: 7296
A5: 2024 | B5: 3880 | C5: 3908 | D5: 937.5 | E5: 0.24 | F5: 256.1 | G5: 0.066 | H5: 110.1 | I5: 0.028 | J5: 10961 | K5: 26920 | L5: 8157
A6: 2025 | B6: 4589 | C6: 4642 | D6: 1104.9 | E6: 0.238 | F6: 285.5 | G6: 0.061 | H6: 94.8 | I6: 0.02 | J6: 11912 | K6: 29790 | L6: 8834

Sheet Форматы
A1: Год | B1: Сеть | C1: Выручка, млрд ₽ | D1: Магазины | E1: Торговая площадь, тыс. м² | F1: Покупки/посещения, млн | G1: Средний чек, ₽ | H1: LFL, % | I1: Рост выручки YoY | J1: Рост магазинов YoY | K1: Выручка на магазин, млн ₽ | L1: Выручка на 1 м², тыс. ₽ | N1: Сеть | O1: Выручка, млрд ₽ | P1: Магазины | Q1: Выручка на магазин, млн ₽ | R1: Выручка на 1 м², тыс. ₽ | S1: Средний чек, ₽ | T1: LFL, %
A2: 2021 | B2: Пятёрочка | C2: 1794 | D2: 17972 | E2: 7048 | F2: 5029 | G2: 409 | H2: 0.056 | I2: - | J2: - | K2: =C2*1000/D2 -> 99.821945 | L2: =C2*1000/E2 -> 254.5403 | N2: Пятёрочка | O2: =C6 -> 3614 | P2: =D6 -> 25533 | Q2: =K6 -> 141.54232 | R2: =L6 -> 366.56862 | S2: =G6 -> 555.3 | T2: =H6 -> 0.106
A3: 2022 | B3: Пятёрочка | C3: 2137 | D3: 19759 | E3: 7728 | F3: 5559 | G3: 441 | H3: 0.117 | I3: =C3/C2-1 -> 0.19119287 | J3: =D3/D2-1 -> 0.09943245 | K3: =C3*1000/D3 -> 108.15325 | L3: =C3*1000/E3 -> 276.52692 | N3: Перекрёсток | O3: =C11 -> 531 | P3: =D11 -> 1004 | Q3: =K11 -> 528.88446 | R3: =L11 -> 480.54299 | S3: =G11 -> 873 | T3: =H11 -> 0.077
A4: 2023 | B4: Пятёрочка | C4: 2571 | D4: 21918 | E4: 8582 | F4: 6391 | G4: 461 | H4: 0.098 | I4: =C4/C3-1 -> 0.20308844 | J4: =D4/D3-1 -> 0.10926666 | K4: =C4*1000/D4 -> 117.30085 | L4: =C4*1000/E4 -> 299.58052 | N4: Чижик | O4: =C16 -> 417.5 | P4: =D16 -> 3253 | Q4: =K12 -> 40.277778 | R4: =L12 -> 142.85714 | S4: =G16 -> 702 | T4: =H16 -> 0.261
A5: 2024 | B5: Пятёрочка | C5: 3114 | D5: 23588 | E5: 9178 | F5: 7002 | G5: 510 | H5: 0.14 | I5: =C5/C4-1 -> 0.21120187 | J5: =D5/D4-1 -> 0.076193083 | K5: =C5*1000/D5 -> 132.01628 | L5: =C5*1000/E5 -> 339.28961
A6: 2025 | B6: Пятёрочка | C6: 3614 | D6: 25533 | E6: 9859 | F6: 7465 | G6: 555.3 | H6: 0.106 | I6: =C6/C5-1 -> 0.16056519 | J6: =D6/D5-1 -> 0.082457182 | K6: =C6*1000/D6 -> 141.54232 | L6: =C6*1000/E6 -> 366.56862
A7: 2021 | B7: Перекрёсток | C7: 349 | D7: 990 | E7: 1099 | F7: 636 | G7: 626 | H7: 0.038 | I7: - | J7: - | K7: =C7*1000/D7 -> 352.52525 | L7: =C7*1000/E7 -> 317.56142
A8: 2022 | B8: Перекрёсток | C8: 385 | D8: 971 | E8: 1085 | F8: 658 | G8: 671 | H8: 0.071 | I8: =C8/C7-1 -> 0.10315186 | J8: =D8/D7-1 -> -0.019191919 | K8: =C8*1000/D8 -> 396.49846 | L8: =C8*1000/E8 -> 354.83871
A9: 2023 | B9: Перекрёсток | C9: 419 | D9: 972 | E9: 1085 | F9: 672 | G9: 713 | H9: 0.083 | I9: =C9/C8-1 -> 0.088311688 | J9: =D9/D8-1 -> 0.0010298661 | K9: =C9*1000/D9 -> 431.06996 | L9: =C9*1000/E9 -> 386.17512
A10: 2024 | B10: Перекрёсток | C10: 491 | D10: 986 | E10: 1096 | F10: 706 | G10: 794 | H10: 0.145 | I10: =C10/C9-1 -> 0.17183771 | J10: =D10/D9-1 -> 0.014403292 | K10: =C10*1000/D10 -> 497.9716 | L10: =C10*1000/E10 -> 447.9927
A11: 2025 | B11: Перекрёсток | C11: 531 | D11: 1004 | E11: 1105 | F11: 694 | G11: 873 | H11: 0.077 | I11: =C11/C10-1 -> 0.081466395 | J11: =D11/D10-1 -> 0.018255578 | K11: =C11*1000/D11 -> 528.88446 | L11: =C11*1000/E11 -> 480.54299
A12: 2021 | B12: Чижик | C12: 2.9 | D12: 72 | E12: 20.3 | F12: 5.9 | G12: 568 | H12: — | I12: - | J12: - | K12: =C12*1000/D12 -> 40.277778 | L12: =C12*1000/E12 -> 142.85714
A13: 2022 | B13: Чижик | C13: 35.9 | D13: 517 | E13: 152.4 | F13: 64.8 | G13: 630 | H13: — | I13: =C13/C12-1 -> 11.37931 | J13: =D13/D12-1 -> 6.1805556 | K13: =C13*1000/D13 -> 69.439072 | L13: =C13*1000/E13 -> 235.5643
A14: 2023 | B14: Чижик | C14: 118.4 | D14: 1500 | E14: 442.1 | F14: 231.9 | G14: 580 | H14: — | I14: =C14/C13-1 -> 2.2980501 | J14: =D14/D13-1 -> 1.901354 | K14: =C14*1000/D14 -> 78.933333 | L14: =C14*1000/E14 -> 267.81271
A15: 2024 | B15: Чижик | C15: 249.5 | D15: 2346 | E15: 686.7 | F15: 449 | G15: 631 | H15: — | I15: =C15/C14-1 -> 1.1072635 | J15: =D15/D14-1 -> 0.564 | K15: =C15*1000/D15 -> 106.35124 | L15: =C15*1000/E15 -> 363.33188
A16: 2025 | B16: Чижик | C16: 417.5 | D16: 3253 | E16: 947.5 | F16: 675.4 | G16: 702 | H16: 0.261 | I16: =C16/C15-1 -> 0.67334669 | J16: =D16/D15-1 -> 0.38661552 | K16: =C16*1000/D16 -> 128.34307 | L16: =C16*1000/E16 -> 440.63325

Sheet Сводная_по_сетям
A1: Сводная выручка по торговым сетям, 2021–2025
B3: Пятёрочка | C3: Перекрёсток | D3: Чижик | E3: Grand Total
A4: Row Labels | E4: Grand Total
A5: 2021 | B5: 1794 | C5: 349 | D5: 2.9 | E5: 2145.9
A6: 2022 | B6: 2137 | C6: 385 | D6: 35.9 | E6: 2557.9
A7: 2023 | B7: 2571 | C7: 419 | D7: 118.4 | E7: 3108.4
A8: 2024 | B8: 3114 | C8: 491 | D8: 249.5 | E8: 3854.5
A9: 2025 | B9: 3614 | C9: 531 | D9: 417.5 | E9: 4562.5
A10: Grand Total | B10: 13230 | C10: 2175 | D10: 824.2 | E10: 16229.2

Sheet Анализ
A1: Год | B1: Рост выручки YoY | C1: Рост чистой прибыли YoY | D1: Рост магазинов YoY | E1: Выручка на магазин, млн ₽ | F1: Выручка на 1 м², тыс. ₽ | G1: Средний чек, ₽ | H1: EBITDA маржа | I1: Чистая маржа | K1: Показатель | L1: CAGR 2021–2025
A2: 2021 | B2: - | C2: - | D2: - | E2: =[1]Основные_Данные!C2*1000/[1]Основные_Данные!K2 -> 115.64483 | F2: =[1]Основные_Данные!C2*1000/[1]Основные_Данные!J2 -> 265.79074 | G2: =[1]Основные_Данные!C2*1000/[1]Основные_Данные!L2 -> 386.36762 | H2: =[1]Основные_Данные!G2 -> 0.075 | I2: =[1]Основные_Данные!I2 -> 0.024 | K2: Выручка | L2: =([1]Основные_Данные!C6/[1]Основные_Данные!C2)^(1/4)-1 -> 0.20454807
A3: 2022 | B3: =[1]Основные_Данные!C3/[1]Основные_Данные!C2-1 -> 0.1814059 | C3: =[1]Основные_Данные!H3/[1]Основные_Данные!H2-1 -> -0.022900763 | D3: =[1]Основные_Данные!K3/[1]Основные_Данные!K2-1 -> 0.11496303 | E3: =[1]Основные_Данные!C3*1000/[1]Основные_Данные!K3 -> 122.53634 | F3: =[1]Основные_Данные!C3*1000/[1]Основные_Данные!J3 -> 288.96284 | G3: =[1]Основные_Данные!C3*1000/[1]Основные_Данные!L3 -> 413.55771 | H3: =[1]Основные_Данные!G3 -> 0.073 | I3: =[1]Основные_Данные!I3 -> 0.02 | K3: Количество магазинов | L3: =([1]Основные_Данные!K6/[1]Основные_Данные!K2)^(1/4)-1 -> 0.11801347
A4: 2023 | B4: =[1]Основные_Данные!C4/[1]Основные_Данные!C3-1 -> 0.20767754 | C4: =[1]Основные_Данные!H4/[1]Основные_Данные!H3-1 -> 0.76367187 | D4: =[1]Основные_Данные!K4/[1]Основные_Данные!K3-1 -> 0.1472788 | E4: =[1]Основные_Данные!C4*1000/[1]Основные_Данные!K4 -> 128.98729 | F4: =[1]Основные_Данные!C4*1000/[1]Основные_Данные!J4 -> 311.20783 | G4: =[1]Основные_Данные!C4*1000/[1]Основные_Данные!L4 -> 431.19518 | H4: =[1]Основные_Данные!G4 -> 0.069 | I4: =[1]Основные_Данные!I4 -> 0.029 | K4: Чистая прибыль | L4: =([1]Основные_Данные!H6/[1]Основные_Данные!H2)^(1/4)-1 -> 0.15976304
A5: 2024 | B5: =[1]Основные_Данные!C5/[1]Основные_Данные!C4-1 -> 0.24221233 | C5: =[1]Основные_Данные!H5/[1]Основные_Данные!H4-1 -> 0.2192691 | D5: =[1]Основные_Данные!K5/[1]Основные_Данные!K4-1 -> 0.10373104 | E5: =[1]Основные_Данные!C5*1000/[1]Основные_Данные!K5 -> 145.17088 | F5: =[1]Основные_Данные!C5*1000/[1]Основные_Данные!J5 -> 356.53681 | G5: =[1]Основные_Данные!C5*1000/[1]Основные_Данные!L5 -> 479.09771 | H5: =[1]Основные_Данные!G5 -> 0.066 | I5: =[1]Основные_Данные!I5 -> 0.028 | K5: Торговая площадь | L5: =([1]Основные_Данные!J6/[1]Основные_Данные!J2)^(1/4)-1 -> 0.094659336
A6: 2025 | B6: =[1]Основные_Данные!C6/[1]Основные_Данные!C5-1 -> 0.18781986 | C6: =[1]Основные_Данные!H6/[1]Основные_Данные!H5-1 -> -0.13896458 | D6: =[1]Основные_Данные!K6/[1]Основные_Данные!K5-1 -> 0.10661218 | E6: =[1]Основные_Данные!C6*1000/[1]Основные_Данные!K6 -> 155.8241 | F6: =[1]Основные_Данные!C6*1000/[1]Основные_Данные!J6 -> 389.69107 | G6: =[1]Основные_Данные!C6*1000/[1]Основные_Данные!L6 -> 525.46978 | H6: =[1]Основные_Данные!G6 -> 0.061 | I6: =[1]Основные_Данные!I6 -> 0.02
K7: Данные для визуализаций
K8: Год | L8: Выручка | M8: EBITDA | N8: Чистая прибыль | O8: Магазины | P8: Валовая маржа | Q8: EBITDA маржа | R8: Чистая маржа
K9: =[1]Основные_Данные!A2 -> 2021 | L9: =[1]Основные_Данные!C2 -> 2205 | M9: =[1]Основные_Данные!F2 -> 164.4 | N9: =[1]Основные_Данные!H2 -> 52.4 | O9: =[1]Основные_Данные!K2 -> 19067 | P9: =[1]Основные_Данные!E2 -> 0.251 | Q9: =[1]Основные_Данные!G2 -> 0.075 | R9: =[1]Основные_Данные!I2 -> 0.024
K10: =[1]Основные_Данные!A3 -> 2022 | L10: =[1]Основные_Данные!C3 -> 2605 | M10: =[1]Основные_Данные!F3 -> 190.5 | N10: =[1]Основные_Данные!H3 -> 51.2 | O10: =[1]Основные_Данные!K3 -> 21259 | P10: =[1]Основные_Данные!E3 -> 0.241 | Q10: =[1]Основные_Данные!G3 -> 0.073 | R10: =[1]Основные_Данные!I3 -> 0.02
K11: =[1]Основные_Данные!A4 -> 2023 | L11: =[1]Основные_Данные!C4 -> 3146 | M11: =[1]Основные_Данные!F4 -> 218.5 | N11: =[1]Основные_Данные!H4 -> 90.3 | O11: =[1]Основные_Данные!K4 -> 24390 | P11: =[1]Основные_Данные!E4 -> 0.241 | Q11: =[1]Основные_Данные!G4 -> 0.069 | R11: =[1]Основные_Данные!I4 -> 0.029
K12: =[1]Основные_Данные!A5 -> 2024 | L12: =[1]Основные_Данные!C5 -> 3908 | M12: =[1]Основные_Данные!F5 -> 256.1 | N12: =[1]Основные_Данные!H5 -> 110.1 | O12: =[1]Основные_Данные!K5 -> 26920 | P12: =[1]Основные_Данные!E5 -> 0.24 | Q12: =[1]Основные_Данные!G5 -> 0.066 | R12: =[1]Основные_Данные!I5 -> 0.028
K13: =[1]Основные_Данные!A6 -> 2025 | L13: =[1]Основные_Данные!C6 -> 4642 | M13: =[1]Основные_Данные!F6 -> 285.5 | N13: =[1]Основные_Данные!H6 -> 94.8 | O13: =[1]Основные_Данные!K6 -> 29790 | P13: =[1]Основные_Данные!E6 -> 0.238 | Q13: =[1]Основные_Данные!G6 -> 0.061 | R13: =[1]Основные_Данные!I6 -> 0.02

Sheet Дашборд
B2: X5 Group — анализ результатов 2021–2025
A37: Ключевые выводы
A39: 1. Рост выручки | E39: 2. Давление на маржу | H39: 3. Чижик — драйвер роста | K39: 4. Эффективность форматов
A40: Выручка X5 выросла с 2 205 до 4 642 млрд ₽. CAGR за 2021–2025 составил 20,45% в год. | E40: Валовая маржа снизилась с 25,1% до 23,8%, а EBITDA-маржа — с 7,5% до 6,1%. Рост сопровождается более низкой рентабельностью. | H40: Доля «Чижика» в выручке трёх форматов выросла примерно с 0,1% до 9,2%. LFL в 2025 году — 26,1%, максимум среди трёх сетей. | K40: «Перекрёсток» лидирует по выручке на магазин: около 528,9 млн ₽ в 2025 году против 141,5 млн ₽ у «Пятёрочки» и 128,3 млн ₽ у «Чижика».
